abi_markdowner/__init__.py
abi_markdowner/abi_markdowner.py
abi_markdowner/file_io.py
abi_markdowner/main.py
abi_markdowner-0.1.19.dist-info/licenses/LICENSE
abi_markdowner-0.1.19.dist-info/METADATA
abi_markdowner-0.1.19.dist-info/WHEEL
abi_markdowner-0.1.19.dist-info/entry_points.txt
abi_markdowner-0.1.19.dist-info/top_level.txt
abi_markdowner-0.1.19.dist-info/RECORD
