Metadata-Version: 2.4
Name: abi-markdowner
Version: 0.1.19
Summary: A tool to convert MultiversX Smart Contract ABI files into Markdown documentation.
Author-email: Kostas Tzoumpas <tzoumpas.ks@gmail.com>
Maintainer-email: Kostas Tzoumpas <tzoumpas.ks@gmail.com>
Project-URL: Homepage, https://github.com/0xk0stas/abi-markdowner
Project-URL: Repository, https://github.com/0xk0stas/abi-markdowner
Project-URL: Issues, https://github.com/0xk0stas/abi-markdowner/issues
Project-URL: Changelog, https://github.com/0xk0stas/abi-markdowner/blob/main/CHANGELOG.md
Keywords: multiversx,abi,documentation,markdown,smart-contracts
Classifier: Development Status :: 4 - Beta
Classifier: Intended Audience :: Developers
Classifier: Operating System :: OS Independent
Classifier: Programming Language :: Python :: 3
Classifier: Programming Language :: Python :: 3.8
Classifier: Programming Language :: Python :: 3.9
Classifier: Programming Language :: Python :: 3.10
Classifier: Programming Language :: Python :: 3.11
Classifier: Programming Language :: Python :: 3.12
Classifier: Programming Language :: Python :: 3.13
Classifier: Topic :: Software Development :: Documentation
Classifier: Topic :: Utilities
Requires-Python: >=3.8
License-File: LICENSE
Requires-Dist: toml>=0.10.2
Provides-Extra: dev
Requires-Dist: pytest>=6.0; extra == "dev"
Requires-Dist: pytest-cov>=3.0.0; extra == "dev"
Provides-Extra: test
Requires-Dist: pytest>=6.0; extra == "test"
Requires-Dist: pytest-cov>=3.0.0; extra == "test"
Dynamic: license-file
